{
  "track": [
    "main"
  ],
  "status": [
    "Technical"
  ],
  "primary_area": [
    "Cognitive Modeling & Cognitive Systems",
    "Computer Vision I",
    "Computer Vision II",
    "Computer Vision III",
    "Constraint Satisfaction and Optimization",
    "Data Mining and Knowledge Management",
    "Domain(s) Of Application",
    "Game Theory and Economic Paradigms",
    "Humans and AI",
    "Intelligent Robotics",
    "Knowledge Representation and Reasoning",
    "Machine Learning I",
    "Machine Learning II",
    "Machine Learning III",
    "Multiagent Systems",
    "Philosophy and Ethics of AI",
    "Planning, Routing, and Scheduling",
    "Reasoning under Uncertainty",
    "Search and Optimization",
    "Speech and Natural Language Processing"
  ],
  "categories": {
    "NLP": [
      "05626",
      "09849",
      "00049",
      "10867",
      "11385",
      "11703",
      "04611",
      "04184",
      "11712",
      "11547",
      "05521",
      "11112",
      "03977",
      "11358",
      "10831",
      "05923",
      "11121",
      "11530",
      "11330",
      "11657",
      "10645",
      "10399",
      "10418",
      "09698",
      "11739",
      "10938",
      "11058",
      "10858",
      "10974",
      "10822",
      "11165",
      "11349",
      "08629",
      "10473",
      "11303"
    ],
    "CV": [
      "04707",
      "01610",
      "03653",
      "01926",
      "02813",
      "03152",
      "02567",
      "01711",
      "00561",
      "01016",
      "00542",
      "00771",
      "02884",
      "01183",
      "07488",
      "03326",
      "01638",
      "03027",
      "01782",
      "00661",
      "01060",
      "00258",
      "03608",
      "00131",
      "02026",
      "07005",
      "02822",
      "02035",
      "08962",
      "05422",
      "00808",
      "03045",
      "00625",
      "03408",
      "00580",
      "08503",
      "02558",
      "00140",
      "05395",
      "01518",
      "02008",
      "01314",
      "00879",
      "01254",
      "00923",
      "00914",
      "08277",
      "02344",
      "06437",
      "02920",
      "00203",
      "02624",
      "07770",
      "03318",
      "00906",
      "03000",
      "09180",
      "00670"
    ],
    "Video": [
      "00444",
      "01620",
      "03090",
      "01237",
      "00230",
      "03598",
      "01482",
      "01674",
      "02262",
      "01890",
      "02786",
      "03300",
      "02866",
      "01846",
      "03517"
    ],
    "Audio": [
      "11020",
      "11220"
    ],
    "Multimodal": [
      "08779",
      "00897",
      "05914",
      "03580"
    ],
    "Other": [
      "04859",
      "09396",
      "10034",
      "07168",
      "09894",
      "03749",
      "07868",
      "10408",
      "06064",
      "10327",
      "07426",
      "01899",
      "06829",
      "11522",
      "11486",
      "07435",
      "04908",
      "03716",
      "09091",
      "07176",
      "10362",
      "00194",
      "03868",
      "04146",
      "11011",
      "04459",
      "10138",
      "06159",
      "09813",
      "03830",
      "00122",
      "00969",
      "10894",
      "06342",
      "05539",
      "04477",
      "06952",
      "09549",
      "03682",
      "01323",
      "02117",
      "02397",
      "08708",
      "11276",
      "06150",
      "08691",
      "07637",
      "02955",
      "00276",
      "07051",
      "06783",
      "03472",
      "09225",
      "06037",
      "06559",
      "02335",
      "11685",
      "06926",
      "05304",
      "00697",
      "10463",
      "05016",
      "06685",
      "09539",
      "04826",
      "04689",
      "08512",
      "01220",
      "03371",
      "04744",
      "05676",
      "08666",
      "03081",
      "07788",
      "07736",
      "10174",
      "06231",
      "01052",
      "03804",
      "04354",
      "06918",
      "09368",
      "05076",
      "05755",
      "08342",
      "11248",
      "00753",
      "00312",
      "10738",
      "00607",
      "03291",
      "02831",
      "07372",
      "10663",
      "05244",
      "08892",
      "05800",
      "05634",
      "08874",
      "05684",
      "08901",
      "10767",
      "06333",
      "06765",
      "00029",
      "07922",
      "10228",
      "01881",
      "09118",
      "06515",
      "05025",
      "02893",
      "07728",
      "01412",
      "06239",
      "06019",
      "02162",
      "10275",
      "07647",
      "00960",
      "11748",
      "04299",
      "04022",
      "10710",
      "07941",
      "02307",
      "08566",
      "03508",
      "03454",
      "02659",
      "09805",
      "05773",
      "06115",
      "10884",
      "10526",
      "03481",
      "10903",
      "04030",
      "07975",
      "11229",
      "00185",
      "11076",
      "09162",
      "00989",
      "02504",
      "02108",
      "05413",
      "04201",
      "10803",
      "02642",
      "04415",
      "01990",
      "09048",
      "02513",
      "00374",
      "06978",
      "09575",
      "03698",
      "08187",
      "05950",
      "07408",
      "05141",
      "03344",
      "09944",
      "02982",
      "07069",
      "01438",
      "07904",
      "06211",
      "04272",
      "09040",
      "02768",
      "01096",
      "04843",
      "05992",
      "05156",
      "07931",
      "09707",
      "05834",
      "03758",
      "09341",
      "04975",
      "05692",
      "08098",
      "08259",
      "07470",
      "10690",
      "07516",
      "05404",
      "08414",
      "04602",
      "07841",
      "08304",
      "00534",
      "08753",
      "04620",
      "03134",
      "08539",
      "00149",
      "03353",
      "04567",
      "05959",
      "08594",
      "11394",
      "11002",
      "10492",
      "01592",
      "07886",
      "00762",
      "02468",
      "03380",
      "09066",
      "07744",
      "08621",
      "09350",
      "08735",
      "05219",
      "02298",
      "09512",
      "07984",
      "07042",
      "02487",
      "02777",
      "03589",
      "06856",
      "10427",
      "07682",
      "03063",
      "01289",
      "03036",
      "04318",
      "03018",
      "07752",
      "03930",
      "00248",
      "08062",
      "04092",
      "01828",
      "00634",
      "10391",
      "06358",
      "01272",
      "01729",
      "00401",
      "01104",
      "11376",
      "09439",
      "09886",
      "05332",
      "08081",
      "02144",
      "00998",
      "01536",
      "06183",
      "10720",
      "07550",
      "00706",
      "11468",
      "07603",
      "02135",
      "08761",
      "01908",
      "00383",
      "07229",
      "09595",
      "04245",
      "04450",
      "04680",
      "10090",
      "08028",
      "04716",
      "05359",
      "04662",
      "04405",
      "01464",
      "07949",
      "06001",
      "01078",
      "00095",
      "00790",
      "07024",
      "08548",
      "00744",
      "00472",
      "11412",
      "02839",
      "02522",
      "08017",
      "03206",
      "08378",
      "04432",
      "06703",
      "10445",
      "11765",
      "07345",
      "03959",
      "06375",
      "09868",
      "04776",
      "07211",
      "04237",
      "05377",
      "11449",
      "06541",
      "07133",
      "01174",
      "06497",
      "05976",
      "08883",
      "01583",
      "07390",
      "00980",
      "09623",
      "02902",
      "10070",
      "02911",
      "00598",
      "02316",
      "03526",
      "10912",
      "10983",
      "04725",
      "05512",
      "06587",
      "04593",
      "08910",
      "03571",
      "01386",
      "08575",
      "04933",
      "08584",
      "07655",
      "03170",
      "09971",
      "09006",
      "11667",
      "09910",
      "02759",
      "03635",
      "07576",
      "10119",
      "03733",
      "03821",
      "06222",
      "00419",
      "00942",
      "03850",
      "04559",
      "03399",
      "06847",
      "02585",
      "03280",
      "05573",
      "10436",
      "09926",
      "06665",
      "04281",
      "11258",
      "03099",
      "09990",
      "08333",
      "01491",
      "09484",
      "07317",
      "06046",
      "09962",
      "06097",
      "05479",
      "09190",
      "08295",
      "04628",
      "00454",
      "04228",
      "06258",
      "02964",
      "05277",
      "10681",
      "09741",
      "02207",
      "08404",
      "00735",
      "08386",
      "08849",
      "00267",
      "05503",
      "07701",
      "09661",
      "11094",
      "02414",
      "02550",
      "02848",
      "00951",
      "05313",
      "04039",
      "04468",
      "05043",
      "04785",
      "09558",
      "07239",
      "07033",
      "07185",
      "04999",
      "09604",
      "11495",
      "07620",
      "07363",
      "07381",
      "09999",
      "03741",
      "08351",
      "01656",
      "09171",
      "08432",
      "08124",
      "06080",
      "01999",
      "08036",
      "06106",
      "10729",
      "03786",
      "05487",
      "09422",
      "05897",
      "06480",
      "05968",
      "10545",
      "09304",
      "09313",
      "00843",
      "04397",
      "09635",
      "10608",
      "09902",
      "10156",
      "08988",
      "05470",
      "10930",
      "10501",
      "04109",
      "07628",
      "04734",
      "02280",
      "07059",
      "11622",
      "09109",
      "03939",
      "10749",
      "03690",
      "04014",
      "09074",
      "08717",
      "00499",
      "00817",
      "09413",
      "05173",
      "08395",
      "10008",
      "08683",
      "11312",
      "01935",
      "06970",
      "04541",
      "06755",
      "09644",
      "07255",
      "06488",
      "06577",
      "08370",
      "08196",
      "07594",
      "06367",
      "08832",
      "04165",
      "07966",
      "02053",
      "11504",
      "06420",
      "00365",
      "06988",
      "02379",
      "04193",
      "11459",
      "00933",
      "07220",
      "03499",
      "00113",
      "07691",
      "01087",
      "05034",
      "09287",
      "04966",
      "04175",
      "10309",
      "10849",
      "11676",
      "11340",
      "02938",
      "04698",
      "01819",
      "08919",
      "08249",
      "03234",
      "09767",
      "05781",
      "05295",
      "06463",
      "09431",
      "08009",
      "06394",
      "03904",
      "11595",
      "11403",
      "03179",
      "01429",
      "11421",
      "08141",
      "04575",
      "10080",
      "10672",
      "06350",
      "11774",
      "08045",
      "03108",
      "01792",
      "00356",
      "06313",
      "06454",
      "06810",
      "05183",
      "11130",
      "03224",
      "10110",
      "11038",
      "01509",
      "07895",
      "10283",
      "11103",
      "02189",
      "02253",
      "09448",
      "05451",
      "09724",
      "09504",
      "04892",
      "05737",
      "10060",
      "02991",
      "10554",
      "02180",
      "01574",
      "06295",
      "00516",
      "06287",
      "07096",
      "07309",
      "02633",
      "09057",
      "01280",
      "08115",
      "01601",
      "04532",
      "07202",
      "09260",
      "05208",
      "07399",
      "05133",
      "07859",
      "01245",
      "11630",
      "06648",
      "02271",
      "01210",
      "03125",
      "00069",
      "06322",
      "11294",
      "11029",
      "11639",
      "06471",
      "06614",
      "00239",
      "10993",
      "05851",
      "01306",
      "08132",
      "02677",
      "01113",
      "08840",
      "00410",
      "03309",
      "10482",
      "06737",
      "09208",
      "00799",
      "10636",
      "10627",
      "05616",
      "00679",
      "06010",
      "06141",
      "11139",
      "07558",
      "08557",
      "06792",
      "06605",
      "07281",
      "01810",
      "07814",
      "08267",
      "01069",
      "03644",
      "07015",
      "04583",
      "06411",
      "06713",
      "06446",
      "07337",
      "01148",
      "03362",
      "07290",
      "07247",
      "09795",
      "07534",
      "04005",
      "02477",
      "02703",
      "01350",
      "00003",
      "06674",
      "04495",
      "06384",
      "02153",
      "10184",
      "01341",
      "06550",
      "03490",
      "01953",
      "01122",
      "02595",
      "00571",
      "09457",
      "08797",
      "01007",
      "01765",
      "03796",
      "09786",
      "09136",
      "08231",
      "05932",
      "08744",
      "07525",
      "08857",
      "00688",
      "05642",
      "04884",
      "08770",
      "08494",
      "10025",
      "10266",
      "01647",
      "03446",
      "10129",
      "09278",
      "04752",
      "06167",
      "00077",
      "01359",
      "02604",
      "05564",
      "08954",
      "03335",
      "09980",
      "10256",
      "09377",
      "10219",
      "09475",
      "00490",
      "01140",
      "04156",
      "01962",
      "03197",
      "02388",
      "10370",
      "05592",
      "05059",
      "03662",
      "09687",
      "11513",
      "08220",
      "08603",
      "04760",
      "01720",
      "05906",
      "01665",
      "00780",
      "06524",
      "04065",
      "09014",
      "04345",
      "10921",
      "10454",
      "03617",
      "02973",
      "01034",
      "00616",
      "00481",
      "03968",
      "06072",
      "06631",
      "05556",
      "01043",
      "11200",
      "09031",
      "09466",
      "02750",
      "04371",
      "07354",
      "05068",
      "01837",
      "02712",
      "01456",
      "06893",
      "00059",
      "05530",
      "04337",
      "04388",
      "05228",
      "06944",
      "05792",
      "04379",
      "11783",
      "06304",
      "07087",
      "05700",
      "06193",
      "06248",
      "09821",
      "04646",
      "04057",
      "01201",
      "08936",
      "02722",
      "02613",
      "01367",
      "03417",
      "02685",
      "08204",
      "00086",
      "09242",
      "08212",
      "10166",
      "10563",
      "04424",
      "08315",
      "06132",
      "10776",
      "06874",
      "11431",
      "02352",
      "10535",
      "10146",
      "11604",
      "03426",
      "04550",
      "01773",
      "04083",
      "08089",
      "05341",
      "08106",
      "04875",
      "10353",
      "05548",
      "05582",
      "05600",
      "05879",
      "10051",
      "07993",
      "09584",
      "02225",
      "10518",
      "11285",
      "02531",
      "07479",
      "01546",
      "08240",
      "06532",
      "05164",
      "04263",
      "09153",
      "09199",
      "09652",
      "05199",
      "05350",
      "02406",
      "00158",
      "09750",
      "07612",
      "09918",
      "08450",
      "00011",
      "07124",
      "07300",
      "03767",
      "03996",
      "06838",
      "07877",
      "10291",
      "01872",
      "08675",
      "10238",
      "02244",
      "05108",
      "02731",
      "01738",
      "02576",
      "03553",
      "11440",
      "03895",
      "06729",
      "09323",
      "07115",
      "09296",
      "03243",
      "00589",
      "09529",
      "01702",
      "09830",
      "00021",
      "05260",
      "10319",
      "10599",
      "00652",
      "08647",
      "07417",
      "08823",
      "04957",
      "04308",
      "03072",
      "00427",
      "01863",
      "02540",
      "03390",
      "11192",
      "04210",
      "08467",
      "09360",
      "10794",
      "00715",
      "07823",
      "05842",
      "09331",
      "01192",
      "05984",
      "10509",
      "11367",
      "11721",
      "10381",
      "06028",
      "09233",
      "00303",
      "03562",
      "05191",
      "05861",
      "09127",
      "10758",
      "07831",
      "10202",
      "00176",
      "04513",
      "08638",
      "00436",
      "11209",
      "08324",
      "08806",
      "09935",
      "00834",
      "01944",
      "04654",
      "00826",
      "05869",
      "07506",
      "07913",
      "03840",
      "02099",
      "05668",
      "09758",
      "06694",
      "05385",
      "07664",
      "06506",
      "11648",
      "02171",
      "05084",
      "08423",
      "08945",
      "06721",
      "10590",
      "03913",
      "08726",
      "06910",
      "06639",
      "06429",
      "01527",
      "02198",
      "02946",
      "02857",
      "02450",
      "04637",
      "05942",
      "00212",
      "03724",
      "09082",
      "02651",
      "10618",
      "01332",
      "08361",
      "08150",
      "09858",
      "03626",
      "09145",
      "05431",
      "07462",
      "04363",
      "10016",
      "08520",
      "06089",
      "09732",
      "05286",
      "05651",
      "08927",
      "11586",
      "00221",
      "03535",
      "04486",
      "01421",
      "03271",
      "07497",
      "00347",
      "08476",
      "03188",
      "04523",
      "10699",
      "02325",
      "04048",
      "11174",
      "11156",
      "00870",
      "00551",
      "06175",
      "03117",
      "05116",
      "07957",
      "07143",
      "03859",
      "09840",
      "08612",
      "09669",
      "08054",
      "02495",
      "06623",
      "08179",
      "05051",
      "08788",
      "10299",
      "09269",
      "03161",
      "10875",
      "02082",
      "07078",
      "04327",
      "02289",
      "11566",
      "06801",
      "03463",
      "02431",
      "00861",
      "01564",
      "01166",
      "01395",
      "11067",
      "11085",
      "02091",
      "01555",
      "06746",
      "06278",
      "03252",
      "03544",
      "11556",
      "02459",
      "04834",
      "09567",
      "09386",
      "07672",
      "07444",
      "03262",
      "01263",
      "04219",
      "06123",
      "01747",
      "01228",
      "05440",
      "04941",
      "01500",
      "08997",
      "06402",
      "06202",
      "07797",
      "04867",
      "01756",
      "04254",
      "06657",
      "02235",
      "09877",
      "04504",
      "10336",
      "07152",
      "00525",
      "09776",
      "01692",
      "08001",
      "08529",
      "10247",
      "08485",
      "06865",
      "07326",
      "09217",
      "08866",
      "09022",
      "03436",
      "11321",
      "07542",
      "01376",
      "09953",
      "01917",
      "09251",
      "05150",
      "08657",
      "02740",
      "00339",
      "00463",
      "08072",
      "10345",
      "03986",
      "05660",
      "02062",
      "09679",
      "10581",
      "01404",
      "03949",
      "02694",
      "02017",
      "06819",
      "04120",
      "08286",
      "02370",
      "08980",
      "09100",
      "01854",
      "03215",
      "05323",
      "05252",
      "05825",
      "03054",
      "07779",
      "11575",
      "00285",
      "10956",
      "11694",
      "03877",
      "04991",
      "04925",
      "05092",
      "10193",
      "07160",
      "11047",
      "09716",
      "04900",
      "03708",
      "04983",
      "07806",
      "05495",
      "04818",
      "05124",
      "04075",
      "03813",
      "05236",
      "06774",
      "07272",
      "04851",
      "06902",
      "01981",
      "06935",
      "10210",
      "01972",
      "10813",
      "06996",
      "00104",
      "09521",
      "05710",
      "05746",
      "02929",
      "00726",
      "00294",
      "08700",
      "10101",
      "02668",
      "01131",
      "00393",
      "01157",
      "07194",
      "11613",
      "01473",
      "05719",
      "05608",
      "05461",
      "08814",
      "06055",
      "00852",
      "10042",
      "02126",
      "00330",
      "02875",
      "02361",
      "02795",
      "04128",
      "07567",
      "11147",
      "07585",
      "07263",
      "03009",
      "04768",
      "04917",
      "03885",
      "04801",
      "04809",
      "05008",
      "03922",
      "02441",
      "01026",
      "10654",
      "02216",
      "00508",
      "03672",
      "01447",
      "06960",
      "05729",
      "11757",
      "10965",
      "04137",
      "10947",
      "05765",
      "01630",
      "04793",
      "04290",
      "04101",
      "09614",
      "08971",
      "07850",
      "02044",
      "11730",
      "01683",
      "00643",
      "06597",
      "03776",
      "05809",
      "08159",
      "11477",
      "00038",
      "00321",
      "11183",
      "08169",
      "02804",
      "02071",
      "00167",
      "11267",
      "00888",
      "01801",
      "06884",
      "05888",
      "11238",
      "04949",
      "05817",
      "08441",
      "07719",
      "07761",
      "09405",
      "05367",
      "02423",
      "09494",
      "03143",
      "08458",
      "10785",
      "05100",
      "10840",
      "01297",
      "04671",
      "06268",
      "04441",
      "10572",
      "11538",
      "06568",
      "07453",
      "07710",
      "07104",
      "05269"
    ]
  }
}