{
  "track": [
    "main"
  ],
  "status": [
    "Oral",
    "Poster",
    "Spotlight"
  ],
  "categories": {
    "NLP": [
      "Comprehension-Guided Referring Expressions",
      "Context-Aware Captions From Context-Agnostic Supervision",
      "Creativity: Generating Diverse Questions Using Variational Autoencoders",
      "Generating Descriptions With Grounded and Co-Referenced People",
      "Interpretable Structure-Evolving LSTM",
      "LSTM Self-Supervision for Detailed Behavior Analysis",
      "Modeling Relationships in Referential Expressions With Compositional Modular Networks",
      "Online Summarization via Submodular and Convex Optimization",
      "Order-Preserving Wasserstein Distance for Sequence Matching",
      "Re-Sign: Re-Aligned End-To-End Sequence Modelling With Deep Recurrent CNN-HMMs",
      "Zero-Shot Classification With Discriminative Semantic Representation Learning"
    ],
    "CV": [
      "3D Human Pose Estimation = 2D Pose Estimation + Matching",
      "3D Convolutional Neural Networks for Efficient and Robust Hand Pose Estimation From Single Depth Images",
      "3D Face Morphable Models “In-The-Wild”",
      "3D Bounding Box Estimation Using Deep Learning and Geometry",
      "3D Human Pose Estimation From a Single Image via Distance Matrix Regression",
      "3D Point Cloud Registration for Localization Using a Deep Neural Network Auto-Encoder",
      "3D Menagerie: Modeling the 3D Shape and Pose of Animals",
      "3D Shape Segmentation With Projective Convolutional Networks",
      "4D Light Field Superpixel and Segmentation",
      "3DMatch: Learning Local Geometric Descriptors From RGB-D Reconstructions",
      "A Combinatorial Solution to Non-Rigid 3D Shape-To-Image Matching",
      "A Generative Model for Depth-Based Robust 3D Facial Pose Tracking",
      "A Domain Based Approach to Social Relation Recognition",
      "A Deep Regression Architecture With Two-Stage Re-Initialization for High Performance Facial Landmark Detection",
      "A Graph Regularized Deep Neural Network for Unsupervised Image Representation Learning",
      "A Hierarchical Approach for Generating Descriptive Image Paragraphs",
      "A New Rank Constraint on Multi-View Fundamental Matrices, and Its Application to Camera Location Recovery",
      "A Minimal Solution for Two-View Focal-Length Estimation Using Two Affine Correspondences",
      "A Non-Convex Variational Approach to Photometric Stereo Under Inaccurate Lighting",
      "A Non-Local Low-Rank Framework for Ultrasound Speckle Reduction",
      "A Point Set Generation Network for 3D Object Reconstruction From a Single Image",
      "A Practical Method for Fully Automatic Intrinsic Camera Calibration Using Directionally Encoded Light",
      "A Reinforcement Learning Approach to the View Planning Problem",
      "A Unified Approach of Multi-Scale Deep and Hand-Crafted Features for Defocus Estimation",
      "Accurate Single Stage Detector Using Recurrent Rolling Convolution",
      "Accurate Optical Flow via Direct Cost Volume Processing",
      "Accurate Depth and Normal Maps From Occlusion-Aware Focal Stack Symmetry",
      "Action-Decision Networks for Visual Tracking With Deep Reinforcement Learning",
      "Acquiring Axially-Symmetric Transparent Objects Using Single-View Transmission Imaging",
      "Active Convolution: Learning the Shape of Convolution for Image Classification",
      "Action Unit Detection With Region Adaptation, Multi-Labeling Learning and Optimal Temporal Fusing",
      "Adaptive Class Preserving Representation for Image Classification",
      "Age Progression/Regression by Conditional Adversarial Autoencoder",
      "All You Need Is Beyond a Good Init: Exploring Better Solution for Training Extremely Deep Convolutional Neural Networks With Orthonormality and Modulation",
      "Aggregated Residual Transformations for Deep Neural Networks",
      "Agent-Centric Risk Assessment: Accident Anticipation and Risky Region Localization",
      "An Efficient Algebraic Solution to the Perspective-Three-Point Problem",
      "Amodal Detection of 3D Objects: Inferring 3D Bounding Boxes From 2D Ones in RGB-Depth Images",
      "An Efficient Background Term for 3D Reconstruction and Tracking With Smooth Surface Models",
      "Asymmetric Feature Maps With Application to Sketch Based Retrieval",
      "ArtTrack: Articulated Multi-Person Tracking in the Wild",
      "Anti-Glare: Tightly Constrained Optimization for Eyeglass Reflection Removal",
      "Are Large-Scale 3D Models Really Necessary for Accurate Visual Localization?",
      "Attend in Groups: A Weakly-Supervised Deep Learning Framework for Learning From Web Data",
      "Attend to You: Personalized Image Captioning With Context Sequence Memory Networks",
      "Attentional Correlation Filter Network for Adaptive Visual Tracking",
      "Attention-Aware Face Hallucination via Deep Reinforcement Learning",
      "Awesome Typography: Statistics-Based Text Effects Transfer",
      "BRISKS: Binary Features for Spherical Images on a Geodesic Grid",
      "BIND: Binary Integrated Net Descriptors for Texture-Less Object Recognition",
      "Benchmarking Denoising Algorithms With Real Photographs",
      "Beyond Instance-Level Image Retrieval: Leveraging Captions to Learn a Global Visual Representation for Semantic Retrieval",
      "Boundary-Aware Instance Segmentation",
      "BranchOut: Regularization for Online Ensemble Tracking With Convolutional Neural Networks",
      "CATS: A Color and Thermal Stereo Benchmark",
      "CASENet: Deep Category-Aware Semantic Edge Detection",
      "CNN-Based Patch Matching for Optical Flow With Thresholded Hinge Embedding Loss",
      "CLEVR: A Diagnostic Dataset for Compositional Language and Elementary Visual Reasoning",
      "CLKN: Cascaded Lucas-Kanade Networks for Image Alignment",
      "CNN-SLAM: Real-Time Dense Monocular SLAM With Learned Depth Prediction",
      "Can Walking and Measuring Along Chord Bunches Better Describe Leaf Shapes?",
      "Cognitive Mapping and Planning for Visual Navigation",
      "Collaborative Deep Reinforcement Learning for Joint Object Search",
      "Coarse-To-Fine Segmentation With Shape-Tailored Continuum Scale Spaces",
      "Coarse-To-Fine Volumetric Prediction for Single-Image 3D Human Pose",
      "Commonly Uncommon: Semantic Sparsity in Situation Recognition",
      "Colorization as a Proxy Task for Visual Understanding",
      "Comparative Evaluation of Hand-Crafted and Learned Local Features",
      "Combining Bottom-Up, Top-Down, and Smoothness Cues for Weakly Supervised Image Segmentation",
      "Consistent-Aware Deep Learning for Person Re-Identification in a Camera Network",
      "Conditional Similarity Networks",
      "Context-Aware Correlation Filter Tracking",
      "Contour-Constrained Superpixels for Image and Video Processing",
      "Counting Everyday Objects in Everyday Scenes",
      "Crossing Nets: Combining GANs and VAEs With a Shared Latent Space for Hand Pose Estimation",
      "Cross-View Image Matching for Geo-Localization in Urban Environments",
      "DSAC - Differentiable RANSAC for Camera Localization",
      "DeLiGAN : Generative Adversarial Networks for Diverse and Limited Data",
      "DUST: Dual Union of Spatio-Temporal Subspaces for Monocular Multiple Object 3D Reconstruction",
      "Deep Crisp Boundaries",
      "Deep Feature Interpolation for Image Content Changes",
      "Deep Image Harmonization",
      "Deep Laplacian Pyramid Networks for Fast and Accurate Super-Resolution",
      "Deep Image Matting",
      "Deep Joint Rain Detection and Removal From a Single Image",
      "Deep Learning Human Mind for Automated Visual Classification",
      "Deep Mixture of Linear Inverse Regressions Applied to Head-Pose Estimation",
      "Deep Matching Prior Network: Toward Tighter Multi-Oriented Text Detection",
      "Deep Level Sets for Salient Object Detection",
      "Deep MANTA: A Coarse-To-Fine Many-Task Network for Joint 2D and 3D Vehicle Analysis From Monocular Image",
      "Deep Multi-Scale Convolutional Neural Network for Dynamic Scene Deblurring",
      "Deep Pyramidal Residual Networks",
      "Deep Representation Learning for Human Motion Prediction and Classification",
      "Deep Quantization: Encoding Convolutional Activations With Deep Generative Model",
      "Deep Roots: Improving CNN Efficiency With Hierarchical Filter Groups",
      "Deep Self-Taught Learning for Weakly Supervised Object Localization",
      "Deep Semantic Feature Matching",
      "Deep Sketch Hashing: Fast Free-Hand Sketch-Based Image Retrieval",
      "Deep Structured Learning for Facial Action Unit Intensity Estimation",
      "Deep TEN: Texture Encoding Network",
      "Deep Variation-Structured Reinforcement Learning for Visual Relationship and Attribute Detection",
      "Deep Visual-Semantic Quantization for Efficient Image Retrieval",
      "Deep View Morphing",
      "Deep Watershed Transform for Instance Segmentation",
      "DeepPermNet: Visual Permutation Learning",
      "Deeply Aggregated Alternating Minimization for Image Restoration",
      "Deeply Supervised Salient Object Detection With Short Connections",
      "DenseReg: Fully Convolutional Dense Shape Regression In-The-Wild",
      "Densely Connected Convolutional Networks",
      "Depth From Defocus in the Wild",
      "Designing Energy-Efficient Convolutional Neural Networks Using Energy-Aware Pruning",
      "Designing Effective Inter-Pixel Information Flow for Natural Image Matting",
      "DeshadowNet: A Multi-Context Embedding Deep Network for Shadow Removal",
      "Designing Illuminant Spectral Power Distributions for Surface Classification",
      "Detailed, Accurate, Human Shape Estimation From Clothed 3D Scan Sequences",
      "Detangling People: Individuating Multiple Close People and Their Body Parts via Region Assembly",
      "Detect, Replace, Refine: Deep Structured Prediction for Pixel Wise Labeling",
      "DeepNav: Learning to Navigate Large Cities",
      "Detecting Masked Faces in the Wild With LLE-CNNs",
      "Detecting Oriented Text in Natural Images by Linking Segments",
      "Differential Angular Imaging for Material Recognition",
      "Dilated Residual Networks",
      "Detecting Visual Relationships With Deep Relational Networks",
      "Direct Photometric Alignment by Mesh Deformation",
      "Discriminative Covariance Oriented Representation Learning for Face Recognition With Image Sets",
      "Discriminative Optimization: Theory and Applications to Point Cloud Registration",
      "Discriminative Correlation Filter With Channel and Spatial Reliability",
      "Disentangled Representation Learning GAN for Pose-Invariant Face Recognition",
      "Diverse Image Annotation",
      "Distinguishing the Indistinguishable: Exploring Structural Ambiguities via Geodesic Context",
      "Diversified Texture Synthesis With Feed-Forward Networks",
      "EAST: An Efficient and Accurate Scene Text Detector",
      "Dynamic Facial Analysis: From Bayesian Filtering to Recurrent Neural Network",
      "Dynamic FAUST: Registering Human Bodies in Motion",
      "ECO: Efficient Convolution Operators for Tracking",
      "Efficient Diffusion on Region Manifolds: Recovering Small Objects With Compact CNN Representations",
      "Efficient Global Point Cloud Alignment Using Bayesian Nonparametric Mixtures",
      "Efficient Linear Programming for Dense CRFs",
      "Efficient Optimization for Hierarchically-structured Interacting Segments (HINTS)",
      "Elastic Shape-From-Template With Spatially Sparse Deforming Forces",
      "End-To-End Representation Learning for Correlation Filter Based Tracking",
      "End-To-End Training of Hybrid CNN-CRF Models for Stereo",
      "End-To-End Instance Segmentation With Recurrent Attention",
      "Episodic CAMN: Contextual Attention-Based Memory Networks With Iterative Feedback for Scene Labeling",
      "Exploiting Saliency for Object Segmentation From Image Level Labels",
      "Exploiting Symmetry and/or Manhattan Properties for 3D Object Structure Estimation From Single and Multiple Images",
      "FASON: First and Second Order Information Fusion Network for Texture Recognition",
      "Exploiting 2D Floorplan for Building-Scale Panorama RGBD Alignment",
      "FC4: Fully Convolutional Color Constancy With Confidence-Weighted Pooling",
      "FCSS: Fully Convolutional Self-Similarity for Dense Semantic Correspondence",
      "Fast Multi-Frame Stereo Scene Flow With Motion Segmentation",
      "Fast Person Re-Identification via Cross-Camera Semantic Binary Transformation",
      "Fast Fourier Color Constancy",
      "Fast Haze Removal for Nighttime Image Using Maximum Reflectance Prior",
      "Feature Pyramid Networks for Object Detection",
      "Fast-At: Fast Automatic Thumbnail Generation Using Deep Neural Networks",
      "FastMask: Segment Multi-Scale Object Candidates in One Shot",
      "Few-Shot Object Recognition From Machine-Labeled Web Images",
      "Fine-Tuning Convolutional Neural Networks for Biomedical Image Analysis: Actively and Incrementally",
      "Fine-To-Coarse Global Registration of RGB-D Scans",
      "Flight Dynamics-Based Recovery of a UAV Trajectory Using Ground Cameras",
      "FlowNet 2.0: Evolution of Optical Flow Estimation With Deep Networks",
      "Forecasting Interactive Dynamics of Pedestrians With Fictitious Play",
      "Fried Binary Embedding for High-Dimensional Visual Features",
      "Forecasting Human Dynamics From Static Images",
      "Fractal Dimension Invariant Filtering and Its CNN-Based Implementation",
      "From Local to Global: Edge Profiles to Camera Motion in Blurred Images",
      "Fully-Adaptive Feature Sharing in Multi-Task Networks With Applications in Person Attribute Classification",
      "G2DeNet: Global Gaussian Distribution Embedding Network and Its Application to Visual Recognition",
      "Fully Convolutional Instance-Aware Semantic Segmentation",
      "Full-Resolution Residual Networks for Semantic Segmentation in Street Scenes",
      "GMS: Grid-based Motion Statistics for Fast, Ultra-Robust Feature Correspondence",
      "Gated Feedback Refinement Network for Dense Image Labeling",
      "Generative Attribute Controller With Conditional Filtered Generative Adversarial Networks",
      "Generating the Future With Adversarial Transformers",
      "Generative Hierarchical Learning of Sparse FRAME Models",
      "Generative Face Completion",
      "Geodesic Distance Descriptors",
      "HSfM: Hybrid Structure-from-Motion",
      "Hallucinating Very Low-Resolution Unaligned and Noisy Face Images by Transformative Discriminative Autoencoders",
      "HPatches: A Benchmark and Evaluation of Handcrafted and Learned Local Descriptors",
      "Hard Mixtures of Experts for Large Scale Weakly Supervised Vision",
      "Hand Keypoint Detection in Single Images Using Multiview Bootstrapping",
      "Hardware-Efficient Guided Image Filtering for Multi-Label Problem",
      "Harvesting Multiple Views for Marker-Less 3D Human Pose Annotations",
      "High-Resolution Image Inpainting Using Multi-Scale Neural Patch Synthesis",
      "IRINA: Iris Recognition (Even) in Inaccurately Segmented Data",
      "Illuminant-Camera Communication to Observe Moving Objects Under Strong External Light by Spread Spectrum Modulation",
      "IM2CAD",
      "Image Deblurring via Extreme Channels Prior",
      "Image Splicing Detection via Camera Response Function Analysis",
      "Image-To-Image Translation With Conditional Adversarial Networks",
      "Image Super-Resolution via Deep Recursive Residual Network",
      "Improved Stereo Matching With Constant Highway Networks and Reflective Confidence Learning",
      "Improving Facial Attribute Prediction Using Semantic Segmentation",
      "Improving RANSAC-Based Segmentation Through CNN Encapsulation",
      "Indoor Scene Parsing With Instance Segmentation, Semantic Labeling and Support Relationship Inference",
      "InstanceCut: From Edges to Instances With MultiCut",
      "Instance-Level Salient Object Segmentation",
      "InterpoNet, a Brain Inspired Neural Network for Optical Flow Dense Interpolation",
      "Interspecies Knowledge Transfer for Facial Keypoint Detection",
      "Joint Detection and Identification Feature Learning for Person Search",
      "Inverse Compositional Spatial Transformer Networks",
      "Joint Geometrical and Statistical Alignment for Visual Domain Adaptation",
      "Joint Multi-Person Pose Estimation and Semantic Part Segmentation",
      "Joint Registration and Representation Learning for Unconstrained Face Identification",
      "Joint Intensity and Spatial Metric Learning for Robust Gait Recognition",
      "Large Kernel Matters — Improve Semantic Segmentation by Global Convolutional Network",
      "L2-Net: Deep Learning of Discriminative Patch Descriptor in Euclidean Space",
      "LCR-Net: Localization-Classification-Regression for Human Pose",
      "LCNN: Lookup-Based Convolutional Neural Network",
      "Latent Multi-View Subspace Clustering",
      "Large Margin Object Tracking With Circulant Feature Maps",
      "Learned Contextual Feature Reweighting for Image Geo-Localization",
      "Learning Adaptive Receptive Fields for Deep Image Parsing Network",
      "Learning Deep CNN Denoiser Prior for Image Restoration",
      "Learning Detailed Face Reconstruction From a Single Image",
      "Learning Deep Context-Aware Features Over Body and Latent Parts for Person Re-Identification",
      "Learning Detection With Diverse Proposals",
      "Learning Deep Match Kernels for Image-Set Classification",
      "Learning Discriminative and Transformation Covariant Local Feature Detectors",
      "Learning Diverse Image Colorization",
      "Learning Dynamic Guidance for Depth Image Enhancement",
      "Learning Features by Watching Objects Move",
      "Learning From Simulated and Unsupervised Images Through Adversarial Training",
      "Learning From Synthetic Humans",
      "Learning Residual Images for Face Attribute Manipulation",
      "Learning Random-Walk Label Propagation for Weakly-Supervised Semantic Segmentation",
      "Learning Non-Maximum Suppression",
      "Learning Non-Lambertian Object Intrinsics Across ShapeNet Categories",
      "Learning Object Interactions and Descriptions for Semantic Image Segmentation",
      "Learning Shape Abstractions by Assembling Volumetric Primitives",
      "Learning Spatial Regularization With Image-Level Supervisions for Multi-Label Image Classification",
      "Learning a Deep Embedding Model for Zero-Shot Learning",
      "Learning to Rank Retargeted Images",
      "Level Playing Field for Million Scale Face Recognition",
      "Learning to Predict Stereo Reliability Enforcing Local Consistency of Confidence Maps",
      "Lifting From the Deep: Convolutional 3D Pose Estimation From a Single Image",
      "Light Field Blind Motion Deblurring",
      "Loss Max-Pooling for Semantic Image Segmentation",
      "Look Into Person: Self-Supervised Structure-Sensitive Learning and a New Benchmark for Human Parsing",
      "Locality-Sensitive Deconvolution Networks With Gated Fusion for RGB-D Indoor Semantic Segmentation",
      "Look Closer to See Better: Recurrent Attention Convolutional Neural Network for Fine-Grained Image Recognition",
      "Low-Rank Embedded Ensemble Semantic Dictionary for Zero-Shot Learning",
      "Low-Rank Bilinear Pooling for Fine-Grained Classification",
      "MCMLSD: A Dynamic Programming Approach to Line Segment Detection",
      "MDNet: A Semantically and Visually Interpretable Medical Image Diagnosis Network",
      "MIML-FCN+: Multi-Instance Multi-Label Learning via Fully Convolutional Networks With Privileged Information",
      "Model-Based Iterative Restoration for Binary Document Image Compression With Dictionary Learning",
      "Minimum Delay Moving Object Detection",
      "Mining Object Parts From CNNs via Active Question-Answering",
      "MuCaLe-Net: Multi Categorical-Level Networks to Generate More Discriminating Features",
      "Multi-Context Attention for Human Pose Estimation",
      "Multi-Object Tracking With Quadruplet Convolutional Neural Networks",
      "Multi-Attention Network for One Shot Learning",
      "Multi-Scale FCN With Cascaded Instance Aware Segmentation for Arbitrary Oriented Word Spotting in the Wild",
      "Multi-Task Correlation Particle Filter for Robust Object Tracking",
      "Multi-View Supervision for Single-View Reconstruction via Differentiable Ray Consistency",
      "Multiple Instance Detection Network With Online Instance Classifier Refinement",
      "Multiple People Tracking by Lifted Multicut and Person Re-Identification",
      "Neural Face Editing With Intrinsic Image Disentangling",
      "Neural Scene De-Rendering",
      "Noise Robust Depth From Focus Using a Ring Difference Filter",
      "Noise-Blind Image Deblurring",
      "Non-Contact Full Field Vibration Measurement Based on Phase-Shifting",
      "Non-Local Color Image Denoising With Convolutional Neural Networks",
      "Non-Local Deep Features for Salient Object Detection",
      "Noisy Softmax: Improving the Generalization Ability of DCNN via Postponing the Early Softmax Saturation",
      "Not Afraid of the Dark: NIR-VIS Face Recognition via Cross-Spectral Hallucination and Low-Rank Embedding",
      "Object Co-Skeletonization With Co-Segmentation",
      "On the Two-View Geometry of Unsynchronized Cameras",
      "On the Effectiveness of Visible Watermarks",
      "On-The-Fly Adaptation of Regression Forests for Online Camera Relocalisation",
      "Online Graph Completion: Multivariate Signal Recovery in Computer Vision",
      "Optical Flow Estimation Using a Spatial Pyramid Network",
      "Optical Flow Requires Multiple Strategies (but Only One Network)",
      "Optical Flow in Mostly Rigid Scenes",
      "Oriented Response Networks",
      "POSEidon: Face-From-Depth for Driver Pose Estimation",
      "Parametric T-Spline Face Morphable Model for Detailed Fitting in Shape Subspace",
      "Parsing Images of Overlapping Organisms With Deep Singling-Out Networks",
      "Perceptual Generative Adversarial Networks for Small Object Detection",
      "Person Re-Identification in the Wild",
      "Pixelwise Instance Segmentation With a Dynamically Instantiated Network",
      "Plug & Play Generative Networks: Conditional Iterative Generation of Images in Latent Space",
      "Point to Set Similarity Based Deep Feature Learning for Person Re-Identification",
      "Physically-Based Rendering for Indoor Scene Understanding Using Convolutional Neural Networks",
      "Physics Inspired Optimization on Semantic Transfer Features: An Alternative Method for Room Layout Estimation",
      "Polyhedral Conic Classifiers for Visual Object Detection and Classification",
      "Polarimetric Multi-View Stereo",
      "PolyNet: A Pursuit of Structural Diversity in Very Deep Networks",
      "PointNet: Deep Learning on Point Sets for 3D Classification and Segmentation",
      "Pose-Aware Person Recognition",
      "PoseAgent: Budget-Constrained 6D Object Pose Estimation via Reinforcement Learning",
      "Predicting Ground-Level Scene Layout From Aerial Imagery",
      "Quad-Networks: Unsupervised Learning to Rank for Interest Point Detection",
      "Pyramid Scene Parsing Network",
      "Product Manifold Filter: Non-Rigid Shape Correspondence via Kernel Density Estimation in the Product Space",
      "Quality Aware Network for Set to Set Recognition",
      "RON: Reverse Connection With Objectness Prior Networks for Object Detection",
      "Radiometric Calibration for Internet Photo Collections",
      "Re-Ranking Person Re-Identification With k-Reciprocal Encoding",
      "ROAM: A Rich Object Appearance Model With Application to Rotoscoping",
      "Real-Time 3D Model Tracking in Color and Depth on a Single CPU Core",
      "Radiometric Calibration From Faces in Images",
      "Reflection Removal Using Low-Rank Matrix Completion",
      "Reflectance Adaptive Filtering Improves Intrinsic Image Estimation",
      "RefineNet: Multi-Path Refinement Networks for High-Resolution Semantic Segmentation",
      "Relationship Proposal Networks",
      "Regressing Robust and Discriminative 3D Morphable Models With a Very Deep Neural Network",
      "Reliable Crowdsourcing and Deep Locality-Preserving Learning for Expression Recognition in the Wild",
      "Removing Rain From Single Images via a Deep Detail Network",
      "Residual Attention Network for Image Classification",
      "Robust Interpolation of Correspondences for Large Displacement Optical Flow",
      "S3Pool: Pooling With Stochastic Spatial Sampling",
      "Robust Visual Tracking Using Oblique Random Forests",
      "SCA-CNN: Spatial and Channel-Wise Attention in Convolutional Networks for Image Captioning",
      "SGM-Nets: Semi-Global Matching With Neural Networks",
      "Scalable Surface Reconstruction From Point Clouds With Extreme Scale and Density Diversity",
      "Saliency Revisited: Analysis of Mouse Movements Versus Fixations",
      "Scalable Person Re-Identification on Supervised Smoothed Manifold",
      "STD2P: RGBD Semantic Segmentation Using Spatio-Temporal Data-Driven Pooling",
      "SRN: Side-output Residual Network for Object Symmetry Detection in the Wild",
      "Scale-Aware Face Detection",
      "ScanNet: Richly-Annotated 3D Reconstructions of Indoor Scenes",
      "Seeing Into Darkness: Scotopic Visual Recognition",
      "Self-Calibration-Based Approach to Critical Motion Sequences of Rolling-Shutter Structure From Motion",
      "Self-Critical Sequence Training for Image Captioning",
      "Seeing What Is Not There: Learning Context to Determine Where Objects Are Missing",
      "Self-Learning Scene-Specific Pedestrian Detectors Using a Progressive Latent Model",
      "Self-Supervised Learning of Visual Features Through Embedding Images Into Text Topic Spaces",
      "Semantic Amodal Segmentation",
      "Semantic Autoencoder for Zero-Shot Learning",
      "Semantic Regularisation for Recurrent Image Annotation",
      "Semantic Image Inpainting With Deep Generative Models",
      "Semantic Multi-View Stereo: Jointly Estimating Objects and Voxels",
      "Semantic Scene Completion From a Single Depth Image",
      "Semantic Segmentation via Structured Patch Prediction, Context CRF and Guidance CRF",
      "Semantically Coherent Co-Segmentation and Reconstruction of Dynamic Scenes",
      "Semi-Calibrated Near Field Photometric Stereo",
      "Simultaneous Facial Landmark Detection, Pose and Deformation Estimation Under Facial Occlusion",
      "Simple Does It: Weakly Supervised Instance and Semantic Segmentation",
      "Simultaneous Feature Aggregating and Hashing for Large-Scale Image Search",
      "Shape Completion Using 3D-Encoder-Predictor CNNs and Shape Synthesis",
      "ShapeOdds: Variational Bayesian Learning of Generative Shape Models",
      "Simultaneous Geometric and Radiometric Calibration of a Projector-Camera Pair",
      "Spatially Adaptive Computation Time for Residual Networks",
      "Spatial-Semantic Image Search by Visual Feature Synthesis",
      "Snapshot Hyperspectral Light Field Imaging",
      "Spatially-Varying Blur Detection Based on Multiscale Fused and Sorted Transform Coefficients of Gradient Magnitudes",
      "Split-Brain Autoencoders: Unsupervised Learning by Cross-Channel Prediction",
      "Stacked Generative Adversarial Networks",
      "SphereFace: Deep Hypersphere Embedding for Face Recognition",
      "Spindle Net: Person Re-Identification With Human Body Region Guided Feature Decomposition and Fusion",
      "Sports Field Localization via Deep Structured Models",
      "StyleBank: An Explicit Representation for Neural Image Style Transfer",
      "Straight to Shapes: Real-Time Detection of Encoded Shapes",
      "Stereo-Based 3D Reconstruction of Dynamic Fluid Surfaces by Global Optimization",
      "Switching Convolutional Neural Network for Crowd Counting",
      "SurfNet: Generating 3D Shape Surfaces Using Deep Residual Networks",
      "SyncSpecCNN: Synchronized Spectral CNN for 3D Shape Segmentation",
      "Surface Motion Capture Transfer With Gaussian Process Regression",
      "Synthesizing 3D Shapes via Modeling Multi-View Depth Maps and Silhouettes With Deep Generative Networks",
      "Synthesizing Normalized Faces From Facial Identity Features",
      "Template Matching With Deformable Diversity Similarity",
      "Template-Based Monocular 3D Recovery of Elastic Shapes Using Lagrangian Multipliers",
      "The Misty Three Point Algorithm for Relative Pose",
      "The Geometry of First-Returning Photons for Non-Line-Of-Sight Imaging",
      "The Surfacing of Multiview 3D Drawings via Lofting and Occlusion Reasoning",
      "The World of Fast Moving Objects",
      "Top-Down Visual Saliency Guided by Captions",
      "Transformation-Grounded Image Generation Network for Novel 3D View Synthesis",
      "Ubernet: Training a Universal Convolutional Neural Network for Low-, Mid-, and High-Level Vision Using Diverse Datasets and Limited Memory",
      "Understanding Traffic Density From Large-Scale Web Camera Data",
      "Unambiguous Text Localization and Retrieval for Cluttered Scenes",
      "UltraStereo: Efficient Learning-Based Matching for Active Stereo Systems",
      "Unite the People: Closing the Loop Between 3D and 2D Human Representations",
      "Unrolling the Shutter: CNN to Correct Motion Distortions",
      "Unsupervised Adaptive Re-Identification in Open World Dynamic Camera Networks",
      "Universal Adversarial Perturbations",
      "Unsupervised Monocular Depth Estimation With Left-Right Consistency",
      "Unsupervised Part Learning for Visual Recognition",
      "Unsupervised Semantic Scene Labeling for Streaming Data",
      "Using Locally Corresponding CAD Models for Dense 3D Reconstructions From a Single Image",
      "Visual Translation Embedding Network for Visual Relation Detection",
      "WSISA: Making Survival Prediction From Whole Slide Histopathological Images",
      "WILDCAT: Weakly Supervised Learning of Deep ConvNets for Image Classification, Pointwise Localization and Segmentation",
      "Weakly Supervised Affordance Detection",
      "Weakly-Supervised Visual Grounding of Phrases With Linguistic Structures",
      "Weakly Supervised Cascaded Convolutional Networks",
      "Wetness and Color From a Single Multispectral Image",
      "Webly Supervised Semantic Segmentation",
      "What Can Help Pedestrian Detection?",
      "What Is and What Is Not a Salient Object? Learning Salient Object Detector by Ensembling Linear Exemplar Regressors",
      "Zero Shot Learning via Multi-Scale Manifold Regularization",
      "Xception: Deep Learning With Depthwise Separable Convolutions",
      "YOLO9000: Better, Faster, Stronger"
    ],
    "Video": [
      "A Multi-View Stereo Benchmark With High-Resolution Images and Multi-Camera Videos",
      "A New Representation of Skeleton Sequences for 3D Action Recognition",
      "A Novel Tensor-Based Video Rain Streaks Removal Approach via Utilizing Discriminatively Intrinsic Priors",
      "ActionVLAD: Learning Spatio-Temporal Aggregation for Action Classification",
      "AdaScan: Adaptive Scan Pooling in Deep Convolutional Neural Networks for Human Action Recognition in Videos",
      "Asynchronous Temporal Fields for Action Recognition",
      "Binary Coding for Partial Action Analysis With Limited Observation Ratios",
      "Binge Watching: Scaling Affordance Learning From Sitcoms",
      "Budget-Aware Deep Semantic Video Segmentation",
      "CERN: Confidence-Energy Recurrent Network for Group Activity Recognition",
      "DESIRE: Distant Future Prediction in Dynamic Scenes With Interacting Agents",
      "Deep 360 Pilot: Learning a Deep Agent for Piloting Through 360° Sports Videos",
      "Deep Feature Flow for Video Recognition",
      "Deep Future Gaze: Gaze Anticipation on Egocentric Videos Using Adversarial Networks",
      "Deep Sequential Context Networks for Action Prediction",
      "Deep Video Deblurring for Hand-Held Cameras",
      "ER3: A Unified Framework for Event Retrieval, Recognition and Recounting",
      "End-To-End Learning of Driving Models From Large-Scale Video Datasets",
      "Fast Video Classification via Adaptive Cascading of Deep Models",
      "Flexible Spatio-Temporal Networks for Video Prediction",
      "FusionSeg: Learning to Combine Motion and Appearance for Fully Automatic Segmentation of Generic Objects in Videos",
      "Global Context-Aware Attention LSTM Networks for 3D Action Recognition",
      "HOPE: Hierarchical Object Prototype Encoding for Efficient Object Instance Search in Videos",
      "Hierarchical Boundary-Aware Neural Encoder for Video Captioning",
      "Identifying First-Person Camera Wearers in Third-Person Videos",
      "Learning Video Object Segmentation From Static Images",
      "Learning to Learn From Noisy Web Videos",
      "Making 360° Video Watchable in 2D: Learning Videography for Click Free Viewing",
      "Modeling Sub-Event Dynamics in First-Person Action Recognition",
      "Modeling Temporal Dynamics and Spatial Configurations of Actions Using Two-Stream Recurrent Neural Networks",
      "Multi-Task Clustering of Human Actions by Sharing Information",
      "Neural Aggregation Network for Video Face Recognition",
      "On Human Motion Prediction Using Recurrent Neural Networks",
      "One-Shot Video Object Segmentation",
      "Online Video Object Segmentation via Convolutional Trident Network",
      "PoseTrack: Joint Multi-Person Pose Estimation and Tracking",
      "Predicting Behaviors of Basketball Players From First Person Videos",
      "Predicting Salient Face in Multiple-Face Videos",
      "Query-Focused Video Summarization: Dataset, Evaluation, and a Memory Network Based Approach",
      "Real-Time Video Super-Resolution With Spatio-Temporal Networks and Motion Compensation",
      "Real-Time Neural Style Transfer for Videos",
      "Recurrent Modeling of Interaction Context for Collective Activity Recognition",
      "S2F: Slow-To-Fast Interpolator Flow",
      "SCC: Semantic Context Cascade for Efficient Action Detection",
      "SPFTN: A Self-Paced Fine-Tuning Network for Segmenting Objects in Weakly Labelled Videos",
      "SST: Single-Stream Temporal Action Proposals",
      "Seeing Invisible Poses: Estimating 3D Body Pose From Egocentric Video",
      "Self-Supervised Video Representation Learning With Odd-One-Out Networks",
      "Simultaneous Stereo Video Deblurring and Scene Flow Estimation",
      "Social Scene Understanding: End-To-End Multi-Person Action Localization and Collective Activity Recognition",
      "Spatio-Temporal Alignment of Non-Overlapping Sequences From Independently Panning Cameras",
      "Spatio-Temporal Self-Organizing Map Deep Network for Dynamic Object Detection From Videos",
      "Spatio-Temporal Naive-Bayes Nearest-Neighbor (ST-NBNN) for Skeleton-Based Action Recognition",
      "Spatiotemporal Multiplier Networks for Video Action Recognition",
      "Spatio-Temporal Vector of Locally Max Pooled Features for Action Recognition in Videos",
      "Surveillance Video Parsing With Single Frame Supervision",
      "Synthesizing Dynamic Patterns by Spatial-Temporal Generative ConvNet",
      "TGIF-QA: Toward Spatio-Temporal Reasoning in Visual Question Answering",
      "Task-Driven Dynamic Fusion: Reducing Ambiguity in Video Description",
      "Temporal Action Co-Segmentation in 3D Motion Capture Data and Videos",
      "Temporal Convolutional Networks for Action Segmentation and Detection",
      "Temporal Action Localization by Structured Maximal Sums",
      "Thin-Slicing Network: A Deep Structured Model for Pose Estimation in Videos",
      "Turning an Urban Scene Video Into a Cinemagraph",
      "Transition Forests: Learning Discriminative Temporal Transitions for Action Recognition and Detection",
      "Unsupervised Learning of Long-Term Motion Dynamics for Videos",
      "Unsupervised Learning of Depth and Ego-Motion From Video",
      "UntrimmedNets for Weakly Supervised Action Recognition and Detection",
      "VidLoc: A Deep Spatio-Temporal Model for 6-DoF Video-Clip Relocalization",
      "Video Acceleration Magnification",
      "Video Propagation Networks",
      "Video2Shop: Exact Matching Clothes in Videos to Online Shopping Images",
      "Video Segmentation via Multiple Granularity Analysis",
      "Video Frame Interpolation via Adaptive Convolution",
      "Video Desnowing and Deraining Based on Matrix Decomposition",
      "Weakly Supervised Dense Video Captioning",
      "Weakly Supervised Semantic Segmentation Using Web-Crawled Videos",
      "Zero-Shot Action Recognition With Error-Correcting Output Codes",
      "YouTube-BoundingBoxes: A Large High-Precision Human-Annotated Data Set for Object Detection in Video"
    ],
    "Audio": [],
    "Multimodal": [
      "AMC: Attention guided Multi-modal Correlation Learning for Image Search",
      "Are You Smarter Than a Sixth Grader? Textbook Question Answering for Multimodal Machine Comprehension",
      "Automatic Understanding of Image and Video Advertisements",
      "Collaborative Summarization of Topic-Related Videos",
      "Connecting Look and Feel: Associating the Visual and Tactile Properties of Physical Materials",
      "Cross-Modality Binary Code Learning via Fusion Similarity Hashing",
      "Deep Cross-Modal Hashing",
      "Deep Multimodal Representation Learning From Temporal Data",
      "Deep Reinforcement Learning-Based Image Captioning With Embedding Reward",
      "Discriminative Bimodal Networks for Visual Localization and Detection With Natural Language Queries",
      "Enhancing Video Summarization via Vision-Language Embedding",
      "Fine-Grained Image Classification via Combining Vision and Language",
      "Generating Holistic 3D Scene Abstractions for Text-Based Image Retrieval",
      "Graph-Structured Representations for Visual Question Answering",
      "GuessWhat?! Visual Object Discovery Through Multi-Modal Dialogue",
      "Joint Sequence Learning and Cross-Modality Convolution for 3D Biomedical Segmentation",
      "Jointly Learning Energy Expenditures and Activities Using Egocentric Multimodal Signals",
      "Learning to Extract Semantic Structure From Documents Using Multimodal Fully Convolutional Neural Networks",
      "Making the v in VQA Matter: Elevating the Role of Image Understanding in Visual Question Answering",
      "Missing Modalities Imputation via Cascaded Residual Autoencoder",
      "Multimodal Transfer: A Hierarchical Deep Convolutional Neural Network for Fast Artistic Style Transfer",
      "Online Asymmetric Similarity Learning for Cross-Modal Retrieval",
      "Semantic Compositional Networks for Visual Captioning",
      "The More You Know: Using Knowledge Graphs for Image Classification",
      "The VQA-Machine: Learning How to Use Existing Vision Algorithms to Answer New Questions",
      "Unsupervised Visual-Linguistic Reference Resolution in Instructional Videos",
      "Video Captioning With Transferred Semantic Attributes",
      "Visual-Inertial-Semantic Scene Representation for 3D Object Detection",
      "Visual Dialog"
    ],
    "Other": [
      "A Clever Elimination Strategy for Efficient Minimal Solvers",
      "A Compact DNN: Approaching GoogLeNet-Level Accuracy of Classification and Domain Adaptation",
      "A Dataset and Exploration of Models for Understanding Video Data Through Fill-In-The-Blank Question-Answering",
      "A Dataset for Benchmarking Image-Based Localization",
      "A Dual Ascent Framework for Lagrangean Decomposition of Combinatorial Problems",
      "A General Framework for Curve and Surface Comparison and Registration With Oriented Varifolds",
      "A Gift From Knowledge Distillation: Fast Optimization, Network Minimization and Transfer Learning",
      "A Joint Speaker-Listener-Reinforcer Model for Referring Expressions",
      "A Low Power, Fully Event-Based Gesture Recognition System",
      "A Linear Extrinsic Calibration of Kaleidoscopic Imaging System From Single 3D Point",
      "A Matrix Splitting Method for Composite Function Minimization",
      "A Message Passing Algorithm for the Minimum Cost Multicut Problem",
      "A Study of Lagrangean Decompositions and Dual Ascent Solvers for Graph Matching",
      "A Wide-Field-Of-View Monocentric Light Field Camera",
      "A-Fast-RCNN: Hard Positive Generation via Adversary for Object Detection",
      "A-Lamp: Adaptive Layout-Aware Multi-Patch Deep Convolutional Neural Network for Photo Aesthetic Assessment",
      "AGA: Attribute-Guided Augmentation",
      "AMVH: Asymmetric Multi-Valued Hashing",
      "Adaptive Relaxed ADMM: Convergence Theory and Practical Implementation",
      "Adaptive and Move Making Auxiliary Cuts for Binary Pairwise Energies",
      "Additive Component Analysis",
      "Adversarial Discriminative Domain Adaptation",
      "Adversarially Tuned Scene Generation",
      "Alternating Direction Graph Matching",
      "An Empirical Evaluation of Visual Question Answering for Novel Objects",
      "An Exact Penalty Method for Locally Convergent Maximum Consensus",
      "Analyzing Computer Vision Data - The Good, the Bad and the Ugly",
      "Annotating Object Instances With a Polygon-RNN",
      "AnchorNet: A Weakly Supervised Network to Learn Geometry-Sensitive Features for Semantic Matching",
      "Attentional Push: A Deep Convolutional Network for Augmenting Image Salience With Shared Attention Modeling in Social Scenes",
      "Automatic Discovery, Association Estimation and Learning of Semantic Attributes for a Thousand Categories",
      "Bayesian Supervised Hashing",
      "Bidirectional Beam Search: Forward-Backward Inference in Neural Sequence Models for Fill-In-The-Blank Image Captioning",
      "Beyond Triplet Loss: A Deep Quadruplet Network for Person Re-Identification",
      "Bidirectional Multirate Reconstruction for Temporal Modeling in Videos",
      "Binarized Mode Seeking for Scalable Visual Pattern Discovery",
      "BigHand2.2M Benchmark: Hand Pose Dataset and State of the Art Analysis",
      "Borrowing Treasures From the Wealthy: Deep Transfer Learning Through Selective Joint Fine-Tuning",
      "Binary Constraint Preserving Graph Matching",
      "Building a Regular Decision Boundary With Deep Networks",
      "CDC: Convolutional-De-Convolutional Networks for Precise Temporal Action Localization in Untrimmed Videos",
      "Captioning Images With Diverse Objects",
      "ChestX-ray8: Hospital-Scale Chest X-Ray Database and Benchmarks on Weakly-Supervised Classification and Localization of Common Thorax Diseases",
      "CityPersons: A Diverse Dataset for Pedestrian Detection",
      "Co-Occurrence Filter",
      "Compact Matrix Factorization With Dependent Subspaces",
      "Computational Imaging on the Electric Grid",
      "Consensus Maximization With Linear Matrix Inequality Constraints",
      "Controlling Perceptual Factors in Neural Style Transfer",
      "Convex Global 3D Registration With Lagrangian Duality",
      "Convolutional Neural Network Architecture for Geometric Matching",
      "Correlational Gaussian Processes for Cross-Domain Visual Recognition",
      "Convolutional Random Walk Networks for Semantic Image Segmentation",
      "DOPE: Distributed Optimization for Pairwise Energies",
      "DeMoN: Depth and Motion Network for Learning Monocular Stereo",
      "Deep Affordance-Grounded Sensorimotor Object Recognition",
      "Deep Co-Occurrence Feature Learning for Visual Object Recognition",
      "Deep Hashing Network for Unsupervised Domain Adaptation",
      "Deep Learning With Low Precision by Half-Wave Gaussian Quantization",
      "Deep Learning of Human Visual Sensitivity in Image Quality Assessment Framework",
      "Deep Learning on Lie Groups for Skeleton-Based Action Recognition",
      "Deep Metric Learning via Facility Location",
      "Deep Multitask Architecture for Integrated 2D and 3D Human Sensing",
      "Deep Network Flow for Multi-Object Tracking",
      "Deep Outdoor Illumination Estimation",
      "Deep Photo Style Transfer",
      "Deep Supervision With Shape Concepts for Occlusion-Aware 3D Object Parsing",
      "Deep Temporal Linear Encoding Networks",
      "Deep Unsupervised Similarity Learning Using Partially Ordered Sets",
      "Dense Captioning With Joint Inference and Visual Context",
      "Discover and Learn New Objects From Documentaries",
      "Discovering Causal Signals in Images",
      "Discretely Coding Semantic Rank Orders for Supervised Image Hashing",
      "Domain Adaptation by Mixture of Alignments of Second- or Higher-Order Scatter Tensors",
      "Dual Attention Networks for Multimodal Reasoning and Matching",
      "Dynamic Attention-Controlled Cascaded Shape Regression Exploiting Training Data Augmentation and Fuzzy-Set Sample Weighting",
      "Dynamic Edge-Conditioned Filters in Convolutional Neural Networks on Graphs",
      "Dynamic Time-Of-Flight",
      "Efficient Multiple Instance Metric Learning Using Weakly Supervised Data",
      "Emotion Recognition in Context",
      "Efficient Solvers for Minimal Problems by Syzygy-Based Reduction",
      "End-To-End 3D Face Reconstruction With Deep Neural Networks",
      "End-To-End Concept Word Detection for Video Captioning, Retrieval, and Question Answering",
      "Exclusivity-Consistency Regularized Multi-View Subspace Clustering",
      "Event-Based Visual Inertial Odometry",
      "Expecting the Unexpected: Training Detectors for Unusual Pedestrians With Adversarial Imposters",
      "Expert Gate: Lifelong Learning With a Network of Experts",
      "FFTLasso: Large-Scale LASSO in the Fourier Domain",
      "Face Normals “In-The-Wild” Using Fully Convolutional Networks",
      "Factorized Variational Autoencoders for Modeling Audience Reactions to Movies",
      "Fast 3D Reconstruction of Faces With Glasses",
      "Fast Boosting Based Detection Using Scale Invariant Multimodal Multiresolution Filtered Features",
      "Feedback Networks",
      "Filter Flow Made Practical: Massively Parallel and Lock-Free",
      "Finding Tiny Faces",
      "Fine-Grained Recognition as HSnet Search for Informative Image Parts",
      "Fine-Grained Recognition of Thousands of Object Categories With Single-Example Training",
      "Fixed-Point Factorized Networks",
      "From Motion Blur to Motion Flow: A Deep Learning Solution for Removing Heterogeneous Motion Blur",
      "From Red Wine to Red Tomato: Composition With Context",
      "From Zero-Shot Learning to Conventional Supervised Classification: Unseen Visual Data Synthesis",
      "Full Resolution Image Compression With Recurrent Neural Networks",
      "Gaze Embeddings for Zero-Shot Image Classification",
      "Generalized Deep Image to Image Regression",
      "General Models for Rational Cameras and the Case of Two-Slit Projections",
      "Generalized Rank Pooling for Activity Recognition",
      "Generalized Semantic Preserving Hashing for N-Label Cross-Modal Retrieval",
      "Geometric Deep Learning on Graphs and Manifolds Using Mixture Model CNNs",
      "Geometric Loss Functions for Camera Pose Regression With Deep Learning",
      "Global Hypothesis Generation for 6D Object Pose Estimation",
      "Global Optimality in Neural Network Training",
      "Grassmannian Manifold Optimization Assisted Sparse Spectral Clustering",
      "Group-Wise Point-Set Registration Based on Rényi's Second Order Entropy",
      "Growing a Brain: Fine-Tuning by Increasing Model Capacity",
      "Harmonic Networks: Deep Translation and Rotation Equivariance",
      "Hidden Layers in Perceptual Learning",
      "Hierarchical Multimodal Metric Learning for Multimodal Classification",
      "Human Shape From Silhouettes Using Generative HKS Descriptors and Cross-Modal Neural Networks",
      "Hyperspectral Image Super-Resolution via Non-Local Sparse Tensor Factorization",
      "Hyper-Laplacian Regularized Unidirectional Low-Rank Tensor Recovery for Multispectral Image Denoising",
      "Improved Texture Networks: Maximizing Quality and Diversity in Feed-Forward Stylization and Texture Synthesis",
      "Improving Interpretability of Deep Neural Networks With Semantic Information",
      "Improving Pairwise Ranking for Multi-Label Image Classification",
      "Improving Training of Deep Neural Networks via Singular Value Bounding",
      "Incorporating Copying Mechanism in Image Captioning for Learning Novel Objects",
      "Incremental Kernel Null Space Discriminant Analysis for Novelty Detection",
      "Infinite Variational Autoencoder for Semi-Supervised Learning",
      "Instance-Aware Image and Sentence Matching With Selective Multimodal LSTM",
      "Intrinsic Grassmann Averages for Online Linear and Robust Subspace Learning",
      "Joint Gap Detection and Inpainting of Line Drawings",
      "Joint Discriminative Bayesian Dictionary and Classifier Learning",
      "Joint Graph Decomposition and Node Labeling: Problem, Algorithms, Applications",
      "Kernel Pooling for Convolutional Neural Networks",
      "Kernel Square-Loss Exemplar Machines for Image Retrieval",
      "KillingFusion: Non-Rigid 3D Reconstruction Without Correspondences",
      "Knowing When to Look: Adaptive Attention via a Visual Sentinel for Image Captioning",
      "Knowledge Acquisition for Visual Question Answering via Iterative Querying",
      "Lean Crowdsourcing: Combining Humans and Machines in an Online System",
      "Learning Barycentric Representations of 3D Shapes for Sketch-Based 3D Shape Retrieval",
      "Learning Category-Specific 3D Shape Models From Weakly Labeled 2D Images",
      "Learning Cross-Modal Deep Representations for Robust Pedestrian Detection",
      "Learning Cross-Modal Embeddings for Cooking Recipes and Food Images",
      "Learning Deep Binary Descriptor With Multi-Quantization",
      "Learning From Noisy Large-Scale Datasets With Minimal Supervision",
      "Learning Fully Convolutional Networks for Iterative Non-Blind Deconvolution",
      "Learning Motion Patterns in Videos",
      "Learning Multifunctional Binary Codes for Both Category and Attribute Oriented Retrieval Tasks",
      "Learning an Invariant Hilbert Space for Domain Adaptation",
      "Learning and Refining of Privileged Information-Based RNNs for Action Recognition From Depth Sequences",
      "Learning by Association — A Versatile Semi-Supervised Training Method for Neural Networks",
      "Learning the Multilinear Structure of Visual Data",
      "Learning to Align Semantic Segmentation and 2.5D Maps for Geolocalization",
      "Learning to Detect Salient Objects With Image-Level Supervision",
      "Light Field Reconstruction Using Deep Convolutional Network on EPI",
      "Link the Head to the “Beak”: Zero Shot Learning From Noisy Text Description at Part Precision",
      "Linking Image and Text With 2-Way Nets",
      "Lip Reading Sentences in the Wild",
      "Local Binary Convolutional Neural Networks",
      "Low-Rank-Sparse Subspace Representation for Robust Regression",
      "Making Deep Neural Networks Robust to Label Noise: A Loss Correction Approach",
      "Material Classification Using Frequency- and Depth-Dependent Time-Of-Flight Distortion",
      "Matrix Tri-Factorization With Manifold Regularizations for Zero-Shot Learning",
      "Matting and Depth Recovery of Thin Structures Using a Focal Stack",
      "Memory-Augmented Attribute Manipulation Networks for Interactive Fashion Search",
      "Mimicking Very Efficient Network for Object Detection",
      "Mind the Class Weight Bias: Weighted Maximum Mean Discrepancy for Unsupervised Domain Adaptation",
      "More Is Less: A More Complicated Network With Less Inference Complexity",
      "Multi-Modal Mean-Fields via Cardinality-Based Clamping",
      "Multi-Level Attention Networks for Visual Question Answering",
      "Multi-Scale Continuous CRFs as Sequential Deep Networks for Monocular Depth Estimation",
      "Multi-View 3D Object Detection Network for Autonomous Driving",
      "Multi-Way Multi-Level Kernel Modeling for Neuroimaging Classification",
      "Multigrid Neural Architectures",
      "Multiple-Scattering Microphysics Tomography",
      "NID-SLAM: Robust Monocular SLAM Using Normalised Information Distance",
      "Network Dissection: Quantifying Interpretability of Deep Visual Representations",
      "Network Sketching: Exploiting Binary Structure in Deep CNNs",
      "Newton-Type Methods for Inference in Higher-Order Markov Random Fields",
      "Non-Uniform Subset Selection for Active Learning in Structured Data",
      "Nonnegative Matrix Underapproximation for Robust Multiple Model Fitting",
      "Not All Pixels Are Equal: Difficulty-Aware Semantic Segmentation via Deep Layer Cascade",
      "Object Detection in Videos With Tubelet Proposal Networks",
      "Object Region Mining With Adversarial Erasing: A Simple Classification to Semantic Segmentation Approach",
      "Object-Aware Dense Semantic Correspondence",
      "OctNet: Learning Deep 3D Representations at High Resolutions",
      "On the Global Geometry of Sphere-Constrained Sparse Blind Deconvolution",
      "On Compressing Deep Models by Low Rank and Sparse Decomposition",
      "One-Shot Metric Learning for Person Re-Identification",
      "One-Shot Hyperspectral Imaging Using Faced Reflectors",
      "One-To-Many Network for Visually Pleasing Compression Artifacts Reduction",
      "Outlier-Robust Tensor PCA",
      "Person Search With Natural Language Description",
      "Personalizing Gesture Recognition Using Hierarchical Bayesian Neural Networks",
      "Photo-Realistic Single Image Super-Resolution Using a Generative Adversarial Network",
      "Photorealistic Facial Texture Inference Using Deep Neural Networks",
      "Position Tracking for Virtual Reality Using Commodity WiFi",
      "Predictive-Corrective Networks for Action Detection",
      "Primary Object Segmentation in Videos Based on Region Augmentation and Reduction",
      "Probabilistic Temporal Subspace Clustering",
      "Procedural Generation of Videos to Train Deep Action Recognition Networks",
      "Provable Self-Representation Based Outlier Detection in a Union of Subspaces",
      "Product Split Trees",
      "Quo Vadis, Action Recognition? A New Model and the Kinetics Dataset",
      "Realtime Multi-Person 2D Pose Estimation Using Part Affinity Fields",
      "Reconstructing Transient Images From Single-Photon Sensors",
      "Recurrent 3D Pose Sequence Machines",
      "Recurrent Convolutional Neural Networks for Continuous Sign Language Recognition by Staged Optimization",
      "Residual Expansion Algorithm: Fast and Effective Optimization for Nonconvex Least Squares Problems",
      "Revisiting Metric Learning for SPD Matrix Based Visual Representation",
      "Revisiting the Variable Projection Method for Separable Nonlinear Least Squares Problems",
      "Richer Convolutional Features for Edge Detection",
      "Robust Energy Minimization for BRDF-Invariant Shape From Light Fields",
      "Riemannian Nonlinear Mixed Effects Models: Analyzing Longitudinal Deformations in Neuroimaging",
      "Robust Joint and Individual Variance Explained",
      "Scene Flow to Action Map: A New Representation for RGB-D Based Action Recognition With Convolutional Neural Networks",
      "Scene Graph Generation by Iterative Message Passing",
      "Scene Parsing Through ADE20K Dataset",
      "Scribbler: Controlling Deep Image Synthesis With Sketch and Color",
      "See the Forest for the Trees: Joint Spatial and Temporal Recurrent Neural Networks for Video-Based Person Re-Identification",
      "Semantically Consistent Regularization for Zero-Shot Recognition",
      "Semi-Supervised Deep Learning for Monocular Depth Map Prediction",
      "Sequential Person Recognition in Photo Albums With a Recurrent Network",
      "Shading Annotations in the Wild",
      "Simultaneous Super-Resolution and Cross-Modality Synthesis of 3D Medical Images Using Weakly-Supervised Joint Convolutional Sparse Coding",
      "Simultaneous Visual Data Completion and Denoising Based on Tensor Rank and Total Variation Minimization and Its Primal-Dual Splitting Algorithm",
      "Single Image Reflection Suppression",
      "Slow Flow: Exploiting High-Speed Cameras for Accurate and Diverse Optical Flow Reference Data",
      "Skeleton Key: Image Captioning by Skeleton-Attribute Decomposition",
      "Soft-Margin Mixture of Regressions",
      "Spatiotemporal Pyramid Network for Video Action Recognition",
      "Specular Highlight Removal in Facial Images",
      "Speed/Accuracy Trade-Offs for Modern Convolutional Object Detectors",
      "StyleNet: Generating Attractive Visual Captions With Styles",
      "Subspace Clustering via Variance Regularized Ridge Regression",
      "Superpixels and Polygons Using Simple Non-Iterative Clustering",
      "Supervising Neural Attention Models for Video Captioning by Human Gaze Data",
      "Superpixel-Based Tracking-By-Segmentation Using Markov Chains",
      "Teaching Compositionality to CNNs",
      "Temporal Attention-Gated Model for Robust Sequence Classification",
      "The Amazing Mysteries of the Gutter: Drawing Inferences Between Panels in Comic Book Narratives",
      "Temporal Residual Networks for Dynamic Scene Recognition",
      "The Impact of Typicality for Informative Representative Selection",
      "The Incremental Multiresolution Matrix Factorization Algorithm",
      "Toroidal Constraints for Two-Point Localization Under High Outlier Ratios",
      "Towards Accurate Multi-Person Pose Estimation in the Wild",
      "Tracking by Natural Language Specification",
      "Towards a Quality Metric for Dense Light Fields",
      "Training Object Class Detectors With Click Supervision",
      "Truncated Max-Of-Convex Models",
      "Unified Embedding and Metric Learning for Zero-Exemplar Event Detection",
      "Unsupervised Pixel-Level Domain Adaptation With Generative Adversarial Networks",
      "Unsupervised Vanishing Point Detection and Camera Calibration From a Single Manhattan Image With Radial Distortion",
      "Unsupervised Video Summarization With Adversarial LSTM Networks",
      "Using Ranking-CNN for Age Estimation",
      "Variational Autoencoded Regression: High Dimensional Regression of Visual Data on Complex Manifold",
      "Variational Bayesian Multiple Instance Learning With Gaussian Processes",
      "ViP-CNN: Visual Phrase Guided Convolutional Neural Network",
      "Viraliency: Pooling Local Virality",
      "Weakly Supervised Action Learning With RNN Based Fine-To-Coarse Modeling",
      "Weakly Supervised Actor-Action Segmentation via Robust Multi-Task Ranking",
      "Weighted-Entropy-Based Quantization for Deep Neural Networks",
      "What Is the Space of Attenuation Coefficients in Underwater Computer Vision?",
      "What's in a Question: Using Visual Questions as a Form of Supervision",
      "Why You Should Forget Luminance Conversion and Do Something Better",
      "Zero-Shot Learning - the Good, the Bad and the Ugly",
      "Zero-Shot Recognition Using Dual Visual-Semantic Mapping Paths",
      "iCaRL: Incremental Classifier and Representation Learning"
    ]
  }
}